{"beliefs": {"internal_resistance": 0.012195121951219511, "cell_failure": 0.975609756097561, "charger_error": 0.012195121951219511}, "entropy": 0.18981727789437777, "raw_response": "{\n  \"diagnosis\": \"cell_failure\",\n  \"confidence\": 0.8,\n  \"evidence\": \"One battery cell is at 3.2V while the others are at 4.1V.\",\n  \"document_ids\": [\"D1\"],\n  \"reasoning\": \"The significant voltage difference between cells suggests a failure or aging issue, consistent with document D1's mention of voltage sags indicating high internal resistance or cell aging.\"\n}", "abstain": false, "parsed": {"diagnosis": "cell_failure", "confidence": 0.8, "evidence": "One battery cell is at 3.2V while the others are at 4.1V.", "document_ids": ["D1"], "reasoning": "The significant voltage difference between cells suggests a failure or aging issue, consistent with document D1's mention of voltage sags indicating high internal resistance or cell aging."}}