{"beliefs": {"motor_order_wrong": 0.012195121951219511, "reversed_prop": 0.975609756097561, "gyro_fault": 0.012195121951219511}, "entropy": 0.18981727789437777, "raw_response": "{\n  \"diagnosis\": \"reversed_prop\",\n  \"confidence\": 0.8,\n  \"evidence\": \"Icing of the pitot tube causes the airspeed sensor to freeze at a constant value regardless of actual speed.\",\n  \"document_ids\": [\"D2\"],\n  \"reasoning\": \"The sudden flip upon takeoff suggests an incorrect airflow reading, which is consistent with icing on the pitot tube.\"\n}", "abstain": false, "parsed": {"diagnosis": "reversed_prop", "confidence": 0.8, "evidence": "Icing of the pitot tube causes the airspeed sensor to freeze at a constant value regardless of actual speed.", "document_ids": ["D2"], "reasoning": "The sudden flip upon takeoff suggests an incorrect airflow reading, which is consistent with icing on the pitot tube."}}